<?xml version="1.0"?>
<!--
Copyright (c) 2021-2026 Project CHIP Authors

Licensed under the Apache License, Version 2.0 (the "License");
you may not use this file except in compliance with the License.
You may obtain a copy of the License at

    http://www.apache.org/licenses/LICENSE-2.0

Unless required by applicable law or agreed to in writing, software
distributed under the License is distributed on an "AS IS" BASIS,
WITHOUT WARRANTIES OR CONDITIONS OF ANY KIND, either express or implied.
See the License for the specific language governing permissions and
limitations under the License.
-->
<!--
XML generated by Alchemy; DO NOT EDIT.
Source: src/service_device_management/BasicInformationCluster.adoc
Parameters: zap ignore-errored provisional-policy=loose sdkRoot=./connectedhomeip/ specRoot=./connectedhomeip-spec/ attribute=ambient-context-sensor,ambientsensing,cameras,cameras-image-rotation,groupcast,hrap-pdc,hrap-tbrd,hvac-thermostat-events,hvac-thermostat-suggestions,improved-capabilities-tcr,partitioned-crl,security-sensor-events-tcr,tcr-smokeco-unmounted-state,temperature-alarm,thread-commissioning ./connectedhomeip-spec/src/service_device_management/BasicInformationCluster.adoc 
Git: 1.6-185-gb051f7083
Alchemy: v1.6.18
-->
<configurator xmlns:xsi="http://www.w3.org/2001/XMLSchema-instance" xsi:noNamespaceSchemaLocation="../../zcl.xsd">
  <domain name=""/>
  <enum name="ColorEnum" type="enum8">
    <cluster code="0x0028"/>
    <item name="Black" value="0x00"/>
    <item name="Navy" value="0x01"/>
    <item name="Green" value="0x02"/>
    <item name="Teal" value="0x03"/>
    <item name="Maroon" value="0x04"/>
    <item name="Purple" value="0x05"/>
    <item name="Olive" value="0x06"/>
    <item name="Gray" value="0x07"/>
    <item name="Blue" value="0x08"/>
    <item name="Lime" value="0x09"/>
    <item name="Aqua" value="0x0A"/>
    <item name="Red" value="0x0B"/>
    <item name="Fuchsia" value="0x0C"/>
    <item name="Yellow" value="0x0D"/>
    <item name="White" value="0x0E"/>
    <item name="Nickel" value="0x0F"/>
    <item name="Chrome" value="0x10"/>
    <item name="Brass" value="0x11"/>
    <item name="Copper" value="0x12"/>
    <item name="Silver" value="0x13"/>
    <item name="Gold" value="0x14"/>
  </enum>

  <enum name="ProductFinishEnum" type="enum8">
    <cluster code="0x0028"/>
    <item name="Other" value="0x00"/>
    <item name="Matte" value="0x01"/>
    <item name="Satin" value="0x02"/>
    <item name="Polished" value="0x03"/>
    <item name="Rugged" value="0x04"/>
    <item name="Fabric" value="0x05"/>
  </enum>

  <struct name="CapabilityMinimaStruct">
    <cluster code="0x0028"/>
    <item fieldId="0" name="CaseSessionsPerFabric" type="int16u" default="3" min="3" max="10000"/>
    <item fieldId="1" name="SubscriptionsPerFabric" type="int16u" default="3" min="3" max="10000"/>
    <item fieldId="2" name="SimultaneousInvocationsSupported" type="int16u" optional="true" min="1" max="10000"/>
    <item fieldId="3" name="SimultaneousWritesSupported" type="int16u" optional="true" min="1" max="10000"/>
    <item fieldId="4" name="ReadPathsSupported" type="int16u" optional="true" min="9" max="10000"/>
    <item fieldId="5" name="SubscribePathsSupported" type="int16u" optional="true" min="3" max="10000"/>
  </struct>

  <struct name="ProductAppearanceStruct">
    <cluster code="0x0028"/>
    <item fieldId="0" name="Finish" type="ProductFinishEnum" max="0x05"/>
    <item fieldId="1" name="PrimaryColor" type="ColorEnum" isNullable="true" max="0x14"/>
  </struct>

  <cluster>
    <domain>General</domain>
    <name>Basic Information</name>
    <code>0x0028</code>
    <define>BASIC_INFORMATION_CLUSTER</define>
    <description>This cluster provides attributes and events for determining basic information about Nodes, which supports both Commissioning and operational determination of Node characteristics, such as Vendor ID, Product ID and serial number, which apply to the whole Node.</description>
    <client init="false" tick="false">true</client>
    <server init="false" tick="false">true</server>
    <globalAttribute code="0xFFFD" side="either" value="6"/>
    <attribute code="0x0000" side="server" name="DataModelRevision" define="DATA_MODEL_REVISION" type="int16u"/>
    <attribute code="0x0001" side="server" name="VendorName" define="VENDOR_NAME" type="char_string" length="32"/>
    <attribute code="0x0002" side="server" name="VendorID" define="VENDOR_ID" type="vendor_id"/>
    <attribute code="0x0003" side="server" name="ProductName" define="PRODUCT_NAME" type="char_string" length="32"/>
    <attribute code="0x0004" side="server" name="ProductID" define="PRODUCT_ID" type="int16u"/>
    <attribute code="0x0005" side="server" name="NodeLabel" define="NODE_LABEL" type="char_string" length="32" writable="true">
      <access op="write" privilege="manage"/>
    </attribute>
    <attribute code="0x0006" side="server" name="Location" define="LOCATION" type="char_string" length="2" minLength="2" writable="true">
      <access op="write" privilege="administer"/>
    </attribute>
    <attribute code="0x0007" side="server" name="HardwareVersion" define="HARDWARE_VERSION" type="int16u" default="0"/>
    <attribute code="0x0008" side="server" name="HardwareVersionString" define="HARDWARE_VERSION_STRING" type="char_string" length="64" minLength="1"/>
    <attribute code="0x0009" side="server" name="SoftwareVersion" define="SOFTWARE_VERSION" type="int32u" default="0"/>
    <attribute code="0x000A" side="server" name="SoftwareVersionString" define="SOFTWARE_VERSION_STRING" type="char_string" length="64" minLength="1"/>
    <attribute code="0x000B" side="server" name="ManufacturingDate" define="MANUFACTURING_DATE" type="char_string" length="16" minLength="8" optional="true">
      <optionalConform/>
    </attribute>
    <attribute code="0x000C" side="server" name="PartNumber" define="PART_NUMBER" type="char_string" length="32" optional="true">
      <optionalConform/>
    </attribute>
    <attribute code="0x000D" side="server" name="ProductURL" define="PRODUCT_URL" type="long_char_string" length="256" optional="true">
      <optionalConform/>
    </attribute>
    <attribute code="0x000E" side="server" name="ProductLabel" define="PRODUCT_LABEL" type="char_string" length="64" optional="true">
      <optionalConform/>
    </attribute>
    <attribute code="0x000F" side="server" name="SerialNumber" define="SERIAL_NUMBER" type="char_string" length="32" optional="true">
      <optionalConform/>
    </attribute>
    <attribute code="0x0010" side="server" name="LocalConfigDisabled" define="LOCAL_CONFIG_DISABLED" type="boolean" default="0" writable="true" optional="true">
      <access op="write" privilege="manage"/>
      <optionalConform/>
    </attribute>
    <attribute code="0x0011" side="server" name="Reachable" define="REACHABLE" type="boolean" default="1" optional="true">
      <optionalConform/>
    </attribute>
    <attribute code="0x0012" side="server" name="UniqueID" define="UNIQUE_ID" type="char_string" length="32" optional="true">
      <otherwiseConform>
        <mandatoryConform>
          <greaterOrEqualTerm>
            <revision value="current"/>
            <revision value="4"/>
          </greaterOrEqualTerm>
        </mandatoryConform>
        <optionalConform/>
      </otherwiseConform>
    </attribute>
    <attribute code="0x0013" side="server" name="CapabilityMinima" define="CAPABILITY_MINIMA" type="CapabilityMinimaStruct"/>
    <attribute code="0x0014" side="server" name="ProductAppearance" define="PRODUCT_APPEARANCE" type="ProductAppearanceStruct" optional="true">
      <optionalConform>
        <greaterOrEqualTerm>
          <revision value="current"/>
          <revision value="2"/>
        </greaterOrEqualTerm>
      </optionalConform>
    </attribute>
    <attribute code="0x0015" side="server" name="SpecificationVersion" define="SPECIFICATION_VERSION" type="int32u" default="0" optional="true">
      <mandatoryConform>
        <greaterOrEqualTerm>
          <revision value="current"/>
          <revision value="3"/>
        </greaterOrEqualTerm>
      </mandatoryConform>
    </attribute>
    <attribute code="0x0016" side="server" name="MaxPathsPerInvoke" define="MAX_PATHS_PER_INVOKE" type="int16u" min="1" default="1" optional="true">
      <mandatoryConform>
        <greaterOrEqualTerm>
          <revision value="current"/>
          <revision value="3"/>
        </greaterOrEqualTerm>
      </mandatoryConform>
    </attribute>
    <attribute code="0x0018" side="server" name="ConfigurationVersion" define="CONFIGURATION_VERSION" type="int32u" min="1" default="1" optional="true">
      <mandatoryConform>
        <greaterOrEqualTerm>
          <revision value="current"/>
          <revision value="6"/>
        </greaterOrEqualTerm>
      </mandatoryConform>
    </attribute>
    <event code="0x0000" name="StartUp" priority="critical" side="server">
      <field fieldId="0" name="SoftwareVersion" type="int32u"/>
      <description>The StartUp event SHALL be generated by a Node as soon as reasonable after completing a boot or reboot process.</description>
    </event>

    <event code="0x0001" name="ShutDown" priority="critical" side="server" optional="true">
      <description>The ShutDown event SHOULD be generated by a Node prior to any orderly shutdown sequence on a best-effort basis.</description>
      <optionalConform/>
    </event>

    <event code="0x0002" name="Leave" priority="info" side="server" optional="true">
      <field fieldId="0" name="FabricIndex" type="fabric_idx" min="1" max="254"/>
      <description>The Leave event SHOULD be generated by a Node prior to permanently leaving a given Fabric, such as when the RemoveFabric command is invoked for a given fabric, or triggered by factory reset or some other manufacturer specific action to disable or reset the operational data in the Node.</description>
      <optionalConform/>
    </event>

    <event code="0x0003" name="ReachableChanged" priority="info" side="server" optional="true">
      <field fieldId="0" name="ReachableNewValue" type="boolean"/>
      <description>This event (when supported) SHALL be generated when there is a change in the Reachable attribute.</description>
      <mandatoryConform>
        <attribute name="Reachable"/>
      </mandatoryConform>
    </event>

  </cluster>
</configurator>
