<?xml version="1.0"?>
<!--
Copyright (c) 2025 Project CHIP Authors

Licensed under the Apache License, Version 2.0 (the "License");
you may not use this file except in compliance with the License.
You may obtain a copy of the License at

    http://www.apache.org/licenses/LICENSE-2.0

Unless required by applicable law or agreed to in writing, software
distributed under the License is distributed on an "AS IS" BASIS,
WITHOUT WARRANTIES OR CONDITIONS OF ANY KIND, either express or implied.
See the License for the specific language governing permissions and
limitations under the License.
-->
<!--
XML generated by Alchemy; DO NOT EDIT.
Source: src/app_clusters/WebRTC_Provider.adoc
Parameters: in-progress 
Git: 0.7-summer-2025-285-g2a2bd1961
-->
<configurator xmlns:xsi="http://www.w3.org/2001/XMLSchema-instance" xsi:noNamespaceSchemaLocation="../../zcl.xsd">
  <domain name="Cameras"/>
  <bitmap name="WebRTCMetadataOptionsBitmap" type="bitmap8">
    <cluster code="0x0553"/>
    <cluster code="0x0554"/>
    <field name="DataTLV" mask="0x01"/>
  </bitmap>

  <enum name="WebRTCEndReasonEnum" type="enum8">
    <cluster code="0x0553"/>
    <cluster code="0x0554"/>
    <item name="IceFailed" value="0x00"/>
    <item name="IceTimeout" value="0x01"/>
    <item name="UserHangup" value="0x02"/>
    <item name="UserBusy" value="0x03"/>
    <item name="Replaced" value="0x04"/>
    <item name="NoUserMedia" value="0x05"/>
    <item name="InviteTimeout" value="0x06"/>
    <item name="AnsweredElsewhere" value="0x07"/>
    <item name="OutOfResources" value="0x08"/>
    <item name="MediaTimeout" value="0x09"/>
    <item name="LowPower" value="0x0A"/>
    <item name="UnknownReason" value="0x0B"/>
  </enum>

  <struct name="ICEServerStruct" apiMaturity="provisional">
    <cluster code="0x0553"/>
    <cluster code="0x0554"/>
    <item fieldId="1" name="urls" array="true" type="char_string"/>
    <item fieldId="2" name="username" type="char_string" optional="true"/>
    <item fieldId="3" name="credential" type="char_string" optional="true"/>
    <item fieldId="4" name="CAID" type="int16u" optional="true"/>
  </struct>

  <struct name="WebRTCSessionStruct" apiMaturity="provisional" isFabricScoped="true">
    <cluster code="0x0553"/>
    <cluster code="0x0554"/>
    <item fieldId="1" name="ID" type="int16u"/>
    <item fieldId="2" name="PeerNodeID" type="node_id"/>
    <item fieldId="3" name="StreamUsage" type="StreamUsageEnum" min="0x00" max="0x03"/>
    <item fieldId="4" name="VideoStreamID" type="int16u" isNullable="true"/>
    <item fieldId="5" name="AudioStreamID" type="int16u" isNullable="true"/>
    <item fieldId="6" name="MetadataOptions" type="WebRTCMetadataOptionsBitmap" default="0x00" min="0x00" max="0x01"/>
  </struct>

  <cluster apiMaturity="provisional">
    <domain>Cameras</domain>
    <name>WebRTC Transport Provider</name>
    <code>0x0553</code>
    <define>WEB_RTC_TRANSPORT_PROVIDER_CLUSTER</define>
    <description>The WebRTC transport provider cluster provides a way for stream providers (e.g. Cameras) to stream or receive their data through WebRTC.</description>
    <client init="false" tick="false">true</client>
    <server init="false" tick="false">true</server>
    <globalAttribute code="0xFFFD" side="either" value="1"/>
    <attribute code="0x0000" side="server" define="CURRENT_SESSIONS" type="array" entryType="WebRTCSessionStruct">
      <description>CurrentSessions</description>
      <access op="read" privilege="manage"/>
    </attribute>
    <command code="0x01" source="client" name="SolicitOffer" isFabricScoped="true" optional="false" response="SolicitOfferResponse">
      <description>Requests that the Provider initiates a new session with the Offer / Answer flow in a way that allows for options to be passed and work with devices needing the standby flow.</description>
      <quality largeMessage="true"/>
      <arg id="1" name="StreamUsage" type="StreamUsageEnum" min="0x00" max="0x03"/>
      <arg id="2" name="VideoStreamID" type="int16u" optional="true" isNullable="true"/>
      <arg id="3" name="AudioStreamID" type="int16u" optional="true" isNullable="true"/>
      <arg id="4" name="ICEServers" array="true" type="ICEServerStruct" optional="true"/>
      <arg id="5" name="ICETransportPolicy" type="char_string" optional="true"/>
      <arg id="6" name="MetadataOptions" type="WebRTCMetadataOptionsBitmap" optional="true" min="0x00" max="0x01"/>
    </command>

    <command code="0x02" source="server" name="SolicitOfferResponse" optional="false" disableDefaultResponse="true">
      <description>This command SHALL be generated in response to a SolicitOffer command.</description>
      <quality largeMessage="true"/>
      <arg id="1" name="WebRTCSessionID" type="int16u"/>
      <arg id="2" name="DeferredOffer" type="boolean"/>
      <arg id="3" name="VideoStreamID" type="int16u" optional="true" isNullable="true"/>
      <arg id="4" name="AudioStreamID" type="int16u" optional="true" isNullable="true"/>
    </command>

    <command code="0x03" source="client" name="ProvideOffer" isFabricScoped="true" optional="false" response="ProvideOfferResponse">
      <description>This command allows an SDP Offer to be set and start a new session.</description>
      <quality largeMessage="true"/>
      <arg id="1" name="WebRTCSessionID" type="int16u" isNullable="true"/>
      <arg id="2" name="SDP" type="char_string"/>
      <arg id="3" name="StreamUsage" type="StreamUsageEnum" min="0x00" max="0x03"/>
      <arg id="4" name="VideoStreamID" type="int16u" optional="true" isNullable="true"/>
      <arg id="5" name="AudioStreamID" type="int16u" optional="true" isNullable="true"/>
      <arg id="6" name="ICEServers" array="true" type="ICEServerStruct" optional="true"/>
      <arg id="7" name="ICETransportPolicy" type="char_string" optional="true"/>
      <arg id="8" name="MetadataOptions" type="WebRTCMetadataOptionsBitmap" optional="true" min="0x00" max="0x01"/>
    </command>

    <command code="0x04" source="server" name="ProvideOfferResponse" optional="false" disableDefaultResponse="true">
      <description>This command contains information about the session and streams created as a response to the requestor&apos;s offer.</description>
      <quality largeMessage="true"/>
      <arg id="1" name="WebRTCSessionID" type="int16u"/>
      <arg id="2" name="VideoStreamID" type="int16u" optional="true" isNullable="true"/>
      <arg id="3" name="AudioStreamID" type="int16u" optional="true" isNullable="true"/>
    </command>

    <command code="0x05" source="client" name="ProvideAnswer" isFabricScoped="true" optional="false">
      <description>This command SHALL be initiated from a Node in response to an Offer that was previously received from a remote peer.</description>
      <quality largeMessage="true"/>
      <arg id="1" name="WebRTCSessionID" type="int16u"/>
      <arg id="2" name="SDP" type="char_string"/>
    </command>

    <command code="0x06" source="client" name="ProvideICECandidates" isFabricScoped="true" optional="false">
      <description>This command allows for string based https://rfc-editor.org/rfc/rfc8839#section-5.1 generated after the initial Offer / Answer exchange, via a JSEP https://datatracker.ietf.org/doc/html/rfc9429#section-4.1.20 event, a DOM https://www.w3.org/TR/webrtc/#dom-rtcpeerconnectioniceevent event, or other WebRTC compliant implementations, to be added to a session during the gathering phase.</description>
      <quality largeMessage="true"/>
      <arg id="1" name="WebRTCSessionID" type="int16u"/>
      <arg id="2" name="ICECandidates" array="true" type="char_string" minLength="1"/>
    </command>

    <command code="0x07" source="client" name="EndSession" isFabricScoped="true" optional="false">
      <description>This command instructs the stream provider to end the WebRTC session.</description>
      <quality largeMessage="true"/>
      <arg id="1" name="WebRTCSessionID" type="int16u"/>
      <arg id="2" name="Reason" type="WebRTCEndReasonEnum" default="0x0B" min="0x00" max="0x0B"/>
    </command>

  </cluster>
</configurator>
